syx_hhh/__init__.py
syx_hhh-10.5.7.dist-info/LICENSE.txt
syx_hhh-10.5.7.dist-info/METADATA
syx_hhh-10.5.7.dist-info/WHEEL
syx_hhh-10.5.7.dist-info/top_level.txt
syx_hhh-10.5.7.dist-info/RECORD
