Metadata-Version: 2.1
Name: syx-hhh
Version: 10.5.7
Summary: Some environments for reinforcement learning.
Author: bug404
Author-email: z19040042@s.upc.edu.cn
Classifier: Programming Language :: Python :: 3
Classifier: License :: OSI Approved :: MIT License
Classifier: Operating System :: OS Independent
License-File: LICENSE.txt
